pytest_jupyter/__init__.py
pytest_jupyter/_version.py
pytest_jupyter/echo_kernel.py
pytest_jupyter/jupyter_client.py
pytest_jupyter/jupyter_core.py
pytest_jupyter/jupyter_server.py
pytest_jupyter/py.typed
pytest_jupyter/pytest_tornasync.py
pytest_jupyter/utils.py
pytest_jupyter-0.10.1.dist-info/METADATA
pytest_jupyter-0.10.1.dist-info/WHEEL
pytest_jupyter-0.10.1.dist-info/licenses/LICENSE
pytest_jupyter-0.10.1.dist-info/RECORD
