Metadata-Version: 2.3
Name: pytest-jupyter
Version: 0.10.1
Summary: A pytest plugin for testing Jupyter libraries and extensions.
Project-URL: Homepage, http://jupyter.org
Project-URL: Funding, https://numfocus.org/donate
Project-URL: Source, https://github.com/jupyter-server/pytest-jupyter
Project-URL: Tracker, https://github.com/jupyter-server/pytest-jupyter/issues
Author-email: Jupyter Development Team <jupyter@googlegroups.com>
License: # Licensing terms
License-File: LICENSE
Keywords: Jupyter,pytest
Classifier: Development Status :: 4 - Beta
Classifier: Framework :: Jupyter
Classifier: License :: OSI Approved :: BSD License
Classifier: Programming Language :: Python
Classifier: Programming Language :: Python :: 3
Requires-Python: >=3.8
Requires-Dist: jupyter-core>=5.7
Requires-Dist: pytest>=7.0
Provides-Extra: client
Requires-Dist: ipykernel>=6.14; extra == 'client'
Requires-Dist: jupyter-client>=7.4.0; extra == 'client'
Requires-Dist: nbformat>=5.3; extra == 'client'
Provides-Extra: docs
Requires-Dist: myst-parser; extra == 'docs'
Requires-Dist: pydata-sphinx-theme; extra == 'docs'
Requires-Dist: sphinx; extra == 'docs'
Requires-Dist: sphinxcontrib-spelling; extra == 'docs'
Provides-Extra: server
Requires-Dist: ipykernel>=6.14; extra == 'server'
Requires-Dist: jupyter-client>=7.4.0; extra == 'server'
Requires-Dist: jupyter-server>=1.21; extra == 'server'
Requires-Dist: nbformat>=5.3; extra == 'server'
Provides-Extra: test
Requires-Dist: pytest-timeout; extra == 'test'
